{
  "fGIlD8iQ0rc": [
    "@williamelliott",
    "@marlenec9870",
    "@leelorraineschafer6983",
    "@guardianangel9517",
    "@cindysutton1091",
    "@RoseHellmer",
    "@gld5129"
  ],
  "I6BmT7zdjVA": [
    "@thia55",
    "@teresaupchurch9032",
    "@kwik2hear915",
    "@JoRamos-j1q",
    "@sherrillnurnberger3933",
    "@LuciaVanolli-d1n",
    "@Wanda-mp8ot",
    "@555Trout",
    "@certaindeaf8315",
    "@chrissyl1464",
    "@esperhickman6502",
    "@richardlevesque2317",
    "@issacnirmalababu7119",
    "@asian_sammy2022",
    "@alicesmith7417",
    "@bonniebrown9685"
  ],
  "kWuX-pfKrJA": [
    "@guardianangel9517"
  ],
  "zHFgoJQlwEY": [
    "@moaski",
    "@Justin-j1f9d"
  ],
  "TOw9JsgYV3s": [
    "@tonysmith1024"
  ],
  "eiVNpnI-7A0": [
    "@frankieplascencia6160",
    "@truthseeker3962",
    "@KennethLampton",
    "@sabejreid2072",
    "@restoringtheamericancovena763",
    "@amygeorge4279",
    "@kandyhill2268",
    "@死の天使-l8o",
    "@michellewilson6249",
    "@JackOddfellow",
    "@tracybormann5067",
    "@kellyblaxton3189",
    "@winni7150",
    "@jkim92677",
    "@karennelson8503",
    "@kflem5585",
    "@esperhickman6502",
    "@dhn.",
    "@Tracy77751",
    "@jamescosby2343",
    "@arlenelowery4063",
    "@LucyandMartyAdams",
    "@carmelitacarmelita6755",
    "@johnmarshall3903",
    "@YareemahLyrics",
    "@MariaBarretta-om8ln",
    "@deanfeldman2505",
    "@denisehurley7139",
    "@randywoodruff9989",
    "@Stash-c2t",
    "@bonniebrown9685",
    "@mark-x7y5d",
    "@bluesman-b2e",
    "@Iamtheisaiah54",
    "@KC6410-mgt",
    "@f5370",
    "@handynothandsome261",
    "@monty2020-i5d",
    "@beckyguillory9705",
    "@DavidStephenson-m7t",
    "@stayreal120",
    "@ValenciaHernandez-m6q",
    "@alicesmith7417",
    "@lewisridenhour6536",
    "@therescueband3691",
    "@paulv8133"
  ],
  "gJp3-HOdX38": [
    "@guardianangel9517",
    "@denisedito3129"
  ],
  "c0HBf9W0m2U": [
    "@geronimokat4500",
    "@ursulasoames8602",
    "@Paul-gh9ky",
    "@donitamossel2385",
    "@Withoutfaith-i8d",
    "@justlm316",
    "@LucyAnnie-b3o",
    "@bobbysutton460",
    "@uppityglivestockian",
    "@orangesandlemons4127",
    "@jillpeel2025",
    "@guardianangel9517",
    "@LuAnneN",
    "@heather5283"
  ],
  "frRfJBL96tc": [
    "@priscillaluckenbach7231",
    "@lolly9080",
    "@danielwilliams1921",
    "@KellyMurdock-nh7pu",
    "@certaindeaf8315",
    "@GodsentMe.",
    "@cindythomas3842",
    "@elishevajones6730",
    "@BenSudotheORIGINAL",
    "@hideho-u9v"
  ],
  "vnDYoNEtl-o": [
    "@DavidJioo"
  ],
  "WX7-8XabGno": [
    "@mcbingoitz8782",
    "@pootthatbak2578",
    "@jw8968-z6g",
    "@paulsteele9150",
    "@charlieturner8124",
    "@gherzome",
    "@eielson1978",
    "@lancelambracht7625",
    "@weispresidentnow",
    "@kenwright8000",
    "@michellewilson6249",
    "@tmc9525",
    "@Dueone1",
    "@rfmsr2",
    "@CitizenSeven500",
    "@JLM-C.",
    "@francady3679",
    "@100women4",
    "@dandyjandon4231",
    "@taconite",
    "@cyanidejunkie",
    "@AmericanMuscle69",
    "@allent208-kf4hv",
    "@JUSTME-s4r9f",
    "@Hellomonsieur-b5o",
    "@TammyHoll",
    "@seagoat651",
    "@eugenemr",
    "@DavidTaitano",
    "@johne.lentonjr1231",
    "@austindenotter19",
    "@555Trout",
    "@agduke3354",
    "@bettersteps",
    "@voiceofreason2168",
    "@tomlusty8376",
    "@Beuwen_The_Dragon",
    "@sherryriojas-drury8582",
    "@nicholasemerson9852",
    "@stingray427man",
    "@Exedore808",
    "@BrandeBabe",
    "@joeshmo2232",
    "@paulgonzales9",
    "@joshdiggs4991",
    "@ShireIO",
    "@bmiles2011",
    "@bradley3412",
    "@Mr.Constitutionalist427"
  ],
  "vBcbnEY4PD8": [
    "@ChristineCava",
    "@serawasneverquitethequietest",
    "@rheamiller148",
    "@darkdan3379",
    "@robertsanders339",
    "@2AAWK",
    "@GinaPhillips-jt2mw",
    "@esperhickman6502",
    "@monkeygraborange",
    "@ranjeetkolita9133",
    "@Christopher080",
    "@chriscarr422",
    "@kellyblaxton3189",
    "@guardianangel9517",
    "@susanll4811",
    "@eyeonyou1554",
    "@sallycarlin243",
    "@bluesman-b2e"
  ],
  "RlVdBxo3d0A": [
    "@guardianangel9517",
    "@yoktor",
    "@bluesman-b2e"
  ],
  "WIfuyYEzCC4": [
    "@LifeLifemoreAbundantly",
    "@chuckwilsn",
    "@GoodGravy-US",
    "@MrAicex3000",
    "@BarbaraWilson-n6r"
  ],
  "pSx6-Xz8UKw": [
    "@JesusisKing-og1hv",
    "@guardianangel9517",
    "@Bardobardo23",
    "@robinchildofgod5"
  ],
  "M_k0wDaA_mM": [
    "@guardianangel9517",
    "@stanleymcomber4844",
    "@ramruikkarnen1037"
  ],
  "9Yvnhik6Yl8": [
    "@chriscarr422"
  ],
  "EzmKieIl3Ps": [
    "@Tounushi",
    "@arlo0011",
    "@ronnienobles6352",
    "@Deborahtunes",
    "@maureencallahan1604",
    "@guardianangel9517",
    "@Sevenlilies"
  ],
  "rEwRLn53tJs": [
    "@guardianangel9517",
    "@mcbingoitz8782"
  ],
  "RIqJRIC_GQE": [
    "@Daniel-ex6sm",
    "@Deborahtunes"
  ],
  "xuqPJ3ACvJs": [
    "@nicksavage4763",
    "@kwik2hear915",
    "@ralphcloar4009",
    "@certaindeaf8315",
    "@guardianangel9517",
    "@eltonwashington596"
  ],
  "znfsIV9hMUY": [
    "@1FastKawboy",
    "@kflem5585",
    "@jackiec498"
  ],
  "YaiGtOQKn3A": [
    "@eyeonyou1554",
    "@Carlos007-z8x",
    "@chrisclark4084"
  ],
  "GiH7H6roxfY": [
    "@guardianangel9517",
    "@saintmig1101"
  ],
  "cP7QxLU9h2o": [
    "@regulator45",
    "@gigicrown1823"
  ],
  "JnNtH8bckcE": [
    "@charliebrown5611",
    "@KAG4Jesus",
    "@certaindeaf8315"
  ],
  "KB5R-GSeprc": [
    "@motorizedlifting2534",
    "@sherryford667",
    "@slchambers1",
    "@JustAnotherPaddy",
    "@sunayakong8537",
    "@HippyCrippler69",
    "@WillieLee-xf6xd",
    "@RoboLiberty",
    "@retrovoid73",
    "@cynthiagonzalez658",
    "@wigsandfluff5729",
    "@EagleOne1999",
    "@cindyhamblin5673",
    "@arlo0011",
    "@graydi66y",
    "@mikeking7381",
    "@JeneseMimiFisher",
    "@morales1961",
    "@norobbery",
    "@RetiredSchoolCook",
    "@skylilly1",
    "@oldgloryhomestead9752",
    "@mrright1068",
    "@TowGunner",
    "@scottw5315",
    "@susanavny8586",
    "@hn376rar",
    "@FoolsAmongUs",
    "@user-ll8be9vt4u",
    "@CatherineSyme",
    "@zgmiroy",
    "@joby1",
    "@PRBB25",
    "@guardianangel9517",
    "@radfordsmith2773",
    "@SeanTheSarcastic",
    "@rickwoodruff8211",
    "@D7024-p6s",
    "@OneLaw214",
    "@jimhrn8522",
    "@briengriffin8351",
    "@HARDMASADA",
    "@ghosttankcommander5397",
    "@nhmooytis7058",
    "@DrGeorgePBurdell-USN-1701",
    "@LookOut681",
    "@raincoast9010",
    "@BrandonMirphy-rb5js",
    "@SkateboardSoldier",
    "@anthonybartlett221"
  ],
  "a8BPZE2I6ME": [
    "@newellbarrett5537",
    "@darrellthoene3291",
    "@Mustapha1963",
    "@100women4",
    "@joeshmo2232",
    "@MDK5000",
    "@daryoushsameyah8329",
    "@SLFYSH",
    "@usafirst1646",
    "@groveh1",
    "@Memphis2010GFC",
    "@guardianangel9517",
    "@beaucurtis7524",
    "@eyeonyou1554",
    "@guymontag1427"
  ],
  "nIB9MDNtOq8": [
    "@DecolonialAccountant",
    "@rhugh02",
    "@MrMajk898",
    "@ollady7968",
    "@informedconstituent",
    "@rickm5853",
    "@JeneseMimiFisher",
    "@chriscarr422",
    "@joebrown9106",
    "@regulator45",
    "@TheRasputinTrabelsi",
    "@charleshodge1873",
    "@guardianangel9517",
    "@Dementore6",
    "@dawnwells524",
    "@sandabear0617",
    "@robertvondarth1730"
  ],
  "zhf4lrylS8I": [
    "@tomjones6777",
    "@pattilemonhouse7911",
    "@jackiec498",
    "@handynothandsome261",
    "@LeDAR-321",
    "@jglow8337"
  ],
  "kbaEJ6bDyvc": [
    "@DebZaragoza1970",
    "@RetiredSchoolCook",
    "@guardianangel9517",
    "@RolandDean-j4i",
    "@sam805236"
  ],
  "dbZDCb27JGI": [
    "@mexicanme2769",
    "@bokendrick6553",
    "@RoyFtz-e3x",
    "@rheamiller148",
    "@MaeRapas",
    "@johnmcjunkin4613",
    "@pamelachurch527",
    "@pattilemonhouse7911",
    "@johncloptop1585",
    "@Blazefork",
    "@therescueband3691",
    "@JeromeIDLaupapa",
    "@kflem5585",
    "@LeDAR-321",
    "@Felonstalk",
    "@teegums2224",
    "@randychris536",
    "@cathybennett8949"
  ],
  "Ie-KNVTUsqQ": [
    "@nicksavage4763",
    "@jeffs6995",
    "@makiavelli6101",
    "@joeystreets3606",
    "@feelincrispy7053",
    "@darrellthoene3291",
    "@kenharper7189",
    "@leslygioia4987",
    "@rbhurley2271",
    "@kimsweeden7389",
    "@uppityglivestockian",
    "@bobwhite3895",
    "@cbone5999",
    "@Mike-ti6hg",
    "@handleyourface",
    "@robmangeri777",
    "@mcoo465",
    "@RichardKirkwood-x2u5m",
    "@DaleDougherty-i3d",
    "@njd2342",
    "@TommyRibs",
    "@sheilagibson982",
    "@kevin982",
    "@wallyirallac9433",
    "@johan2day",
    "@DonaldStrubhar",
    "@MrWilly2204",
    "@georgeallen1759",
    "@graphguy",
    "@becka42",
    "@StuMas",
    "@Beaglemom4",
    "@poppyd9758",
    "@manningchiro",
    "@cirosalek392",
    "@brandonroeder2461",
    "@Pancho-villa666",
    "@DymaxionDon",
    "@craigmignone2863",
    "@GORDONRICHARDSON-v7h",
    "@MathewPaul-g4x",
    "@Mitz-p1g",
    "@davidcaunter5346",
    "@MikeJones-rk1un",
    "@MontyReed-g1b",
    "@runrunrun54",
    "@Yourmoma8one",
    "@gapa0429",
    "@kennynichols1558",
    "@calinabtx"
  ],
  "Nh9FNd_xxrQ": [
    "@barrym.259",
    "@regulator45",
    "@dwm5150",
    "@jimmyjames6318",
    "@rickdean9623",
    "@bluartz8158",
    "@be_offended_Rumble",
    "@ZezimaMills",
    "@ngcmnh",
    "@dentonhopkins5097",
    "@mimib2152",
    "@onealmason5046",
    "@jcblazak6356",
    "@thepro3729",
    "@Sunshine-n1n",
    "@billyost1479",
    "@Michelle-kj7wv",
    "@erichinkle8522",
    "@msjanzzee"
  ],
  "ifRMjNsl3Cs": [
    "@gerrykings187",
    "@Neilfachman1234",
    "@ryangaaserud678",
    "@pattilemonhouse7911",
    "@zacsayer1818",
    "@charlesschindler7433",
    "@AnnPrince-d4y"
  ],
  "Dr0WLWW-8lg": [
    "@maryjacobs1226",
    "@ron-om1qh",
    "@bobbyboombatz1489",
    "@caliconservative20",
    "@ranjeetkolita9133",
    "@kevin6293",
    "@Joe-pc3hs",
    "@saltysoldier68"
  ],
  "BQOHgUxX37o": [
    "@NickHollingsworth-t6y",
    "@meliciousgoremay",
    "@LarryGee-l9p",
    "@tammycarlson5111",
    "@KeithChristian-z4g",
    "@mrs.rogersneighborhood",
    "@SLFYSH",
    "@donnaconrad7374",
    "@ericmccolough2482",
    "@splash20100",
    "@2AAWK",
    "@toxicavenger2216",
    "@chrisdarwin4887",
    "@mikemarlow1865",
    "@briankristensen349",
    "@Jose-p1k3b",
    "@robertpashka4924",
    "@chriserskine6879",
    "@Time2getgoin",
    "@matthewlightfritz2003",
    "@craigcampbell7401",
    "@khloesmemaw",
    "@smokeyjoe127",
    "@ruthbasehore",
    "@drock1033",
    "@willblackerby9055",
    "@HeavyMetalsCollector",
    "@yasha33etsy",
    "@jamesleibiger8278",
    "@stevebell8525",
    "@guardianangel9517",
    "@loispatterson4814",
    "@williehenson1935",
    "@eyeonyou1554",
    "@loadedhot1034",
    "@lynaustin399",
    "@mikedavis6646",
    "@sxejam518",
    "@edkennedy8765",
    "@JosephMeeks-d1b",
    "@JohnZapata-h5u",
    "@MikeBohrer",
    "@stevespanos75",
    "@user-vf3mp6lp7d"
  ],
  "_JDBu6lnhWY": [
    "@b-man1232",
    "@MrTruthTeller777",
    "@noneofyourbusiness-c3b",
    "@naptownt7197",
    "@dominicvell2309",
    "@Connie-t9u",
    "@therescueband3691",
    "@rocketeer380",
    "@khannwolf4240",
    "@rick101572",
    "@douglasdailey5998",
    "@moncadamendez2456",
    "@morningflowerB",
    "@jean-pascalheynemand3271",
    "@TonyMunzo",
    "@lookyoureyes44",
    "@robinbowen4348",
    "@DaveHanper",
    "@lindataylor8972",
    "@edbiernot4852",
    "@brydenthrasher1278",
    "@Michele-ex2nc",
    "@jesselagunas9961",
    "@Blk_American_Patriotic_Veteran",
    "@ranjeetkolita9133",
    "@forevergreyJV",
    "@marthafridley3115",
    "@randywoodruff9989",
    "@jimhrn8522",
    "@rools2roolsproject325",
    "@guardianangel9517",
    "@jeannettejones6489",
    "@jduncan20879",
    "@simpletonsunshine",
    "@henrynanini2328",
    "@JohnZapata-h5u",
    "@ramon78433",
    "@arandomyoutubernotreally9496"
  ],
  "cRfA42sykm4": [
    "@questaskybreezy1338",
    "@stevep9041"
  ],
  "b3Jef_BI-jA": [
    "@fearnot8218",
    "@rand8025",
    "@ProfessorPoofy",
    "@guardianangel9517",
    "@rodneyjarvis676"
  ],
  "ztZbrqVH3Gg": [
    "@xdsclubgold123",
    "@Zangetsu2026",
    "@darkdan3379",
    "@JackOpenheimer-k3h",
    "@pattilemonhouse7911",
    "@ogden_toto",
    "@logisticalnightmare-b3i",
    "@MDK5000",
    "@inforestsweheal",
    "@msjanzzee",
    "@faith5563",
    "@07MoPower",
    "@billhillyer334",
    "@daniel51404",
    "@guardianangel9517",
    "@JeffDepuy",
    "@JWLuke787",
    "@dososos"
  ],
  "KZ6a5Mfmvnw": [
    "@kimmerdkd",
    "@elwerouno1",
    "@lauriaktahi",
    "@bettyalford1364",
    "@LeDAR-321",
    "@BruHause",
    "@KAG4Jesus"
  ],
  "kP5ZlXEOhA0": [
    "@BRLvisonz",
    "@priscillaluckenbach7231",
    "@simplerway489",
    "@annettehunter2480",
    "@richardlazear4771",
    "@AMX86",
    "@copisetic1104",
    "@HiAuntchovie",
    "@nwaubaniogogooriaku9879",
    "@kathycox1273",
    "@CholaGomez-qf3mo",
    "@edwardrich2564",
    "@LetsfixAmercia",
    "@RenèeL_Panhandle",
    "@HS-iv8wr",
    "@JeneseMimiFisher",
    "@certaindeaf8315",
    "@xyyx1001",
    "@mileslong9675",
    "@a.b.6972",
    "@jackbooten2681",
    "@nancyggg2",
    "@azukarzuchastux8066",
    "@dannyg402012",
    "@maryannerazzano7692",
    "@SteelOvaries",
    "@arfift33n",
    "@BusterChops4252",
    "@Wounderbug23",
    "@WVShawn",
    "@michaelbabella1103",
    "@guardianangel9517",
    "@david50028",
    "@charlesmalchow6802",
    "@brokenwrench404",
    "@johnwadsworth4916",
    "@jasondgillis",
    "@tommmmo1981",
    "@LifeLifemoreAbundantly",
    "@phillipchavez856",
    "@robertbannan6437",
    "@marieswann3204",
    "@dratt1957",
    "@ShireIO",
    "@msudawgma",
    "@jameshildebrand907",
    "@sadwingsraging3044",
    "@sirrenn1936"
  ],
  "oOjv52bG-Ss": [
    "@teresabarrett3266",
    "@selinagross1410",
    "@catpahno1286",
    "@kellywalls1902",
    "@uppityglivestockian",
    "@jamesbaker3153"
  ],
  "SviF_zXK4hU": [
    "@nicksavage4763",
    "@lonnymannino",
    "@kevin982",
    "@drock5404",
    "@johnwood551",
    "@anmvcinco",
    "@regulator45",
    "@ZAXBYTheThird"
  ],
  "vDOVjUGwZCA": [
    "@suerogerts4330",
    "@whydoewhy",
    "@Timbo_Slice23",
    "@VictorJeffcoat",
    "@pr6vide",
    "@sickfloww168",
    "@justwatchingvideos7944",
    "@paulgonzales9",
    "@angelabarnes7588",
    "@Shawnjuan123",
    "@Wavyonthemoon",
    "@regulator45",
    "@SamTheDriver214",
    "@luzmilaloaiza6149",
    "@AngerFPV",
    "@HeidiHundelt",
    "@dannywhatley4900"
  ],
  "uCX88et367Q": [
    "@caliconservative20",
    "@msjanzzee",
    "@montecallaway1886"
  ],
  "-xmtq7Bm9p8": [
    "@sebastiantiralosi9266",
    "@tdurham5499",
    "@xerioussunblade",
    "@danielcox1602",
    "@jameshenderson3916",
    "@finnfey3077"
  ],
  "fG4uQQviAjw": [
    "@wandalebron6897",
    "@rosielahrman2033",
    "@elwerouno1",
    "@rodneyporter1035",
    "@michaelconner1771",
    "@regulator45",
    "@nathannan55",
    "@tresastover5344",
    "@billhillyer334",
    "@TheMichaelLeague144",
    "@andreweden9405",
    "@estherkurtzhals185",
    "@billmahaffey3197",
    "@johnr.lowther7718",
    "@garyjenkins2500",
    "@Fat12219",
    "@DavidSmith-fz8ju",
    "@rhondaenglish4022",
    "@carolyndevall58"
  ],
  "PDKjizLR024": [
    "@certaindeaf8315",
    "@tillyvee6147"
  ],
  "gONQ8xZsq58": [
    "@LouisReed",
    "@MortenAbildgaard-h2z",
    "@rollerskatertexasgirl",
    "@tdurham5499",
    "@Francescathecat",
    "@maritucci4054",
    "@HiAuntchovie",
    "@kevin982",
    "@paulgonzales9",
    "@rebeccabearce2963",
    "@paulaglenn388",
    "@matrikzdaclown7496"
  ],
  "c8aScwIppdE": [
    "@elgrande3934",
    "@ambersmith8884",
    "@nessuno6110",
    "@Marlietterg",
    "@kurtroufosse1693",
    "@laurahunter1690",
    "@richardkeough5332"
  ],
  "kT3fJMB2WDE": [
    "@gilbertosolis9637",
    "@raywilson353",
    "@TerriEoff",
    "@fahq1158",
    "@jimwilder5578",
    "@charlesclampitt5067",
    "@clamcurtains",
    "@gotclay1",
    "@maynunal",
    "@conservativenellie5876",
    "@BillHickman-s3e",
    "@korismith3293",
    "@shaneelliott1272"
  ],
  "DMzrW0qp5sw": [
    "@coro599",
    "@Jonesy11B",
    "@MortenAbildgaard-h2z",
    "@justshutup-i2p",
    "@paulgonzales9",
    "@gordonhill6458",
    "@sadwingsraging3044"
  ],
  "J_o7bqS-1lY": [
    "@derrickmalone3129",
    "@yakobhufer2878",
    "@badkarma6181",
    "@franciscojensen7257",
    "@2AAWK",
    "@paulgonzales9",
    "@donaldsmullen5595",
    "@regulator45",
    "@TimJacobson-o4k",
    "@mikemidisland7114",
    "@therescueband3691",
    "@BarbaraWilson-n6r"
  ],
  "I6y4ZQO3Brw": [
    "@stupidtube9",
    "@LisaDixon-o1z",
    "@AlexM-b9w",
    "@dianeduquette4531",
    "@lowbudgettheory",
    "@joeshmo2232",
    "@IrishAuntie",
    "@jameshenderson3916",
    "@expo2000000",
    "@Purestar777",
    "@lauriehall4025",
    "@LynnetteMcCreery",
    "@beaucurtis7524"
  ],
  "eLOWY8nSIC0": [
    "@SB-cp9re",
    "@CaptKat3",
    "@valenz2006",
    "@gabelisa1",
    "@JeffDepuy",
    "@sherrythompson2035",
    "@Paul-x4p7b",
    "@Zodiac_C87",
    "@donaldsmullen5595",
    "@cyanidejunkie",
    "@nicolebaise4286",
    "@bleedingsnowman67",
    "@jaypratt1862",
    "@stevespradley8809",
    "@MrGabrielJude",
    "@rheamiller148",
    "@rickreasoner8664",
    "@AcutePumpkinClodHopper",
    "@hildaburger64",
    "@kellywalls1902",
    "@robertarena6731",
    "@ranjeetkolita9133",
    "@sheliahumphrey4402",
    "@chuckwilsn",
    "@surfer103",
    "@pathfinder5804",
    "@paulgonzales9",
    "@Alaskan_Deplorable",
    "@gwoodgwood",
    "@donnawyas332"
  ],
  "v7TS1pH9rlY": [
    "@cvincent2340",
    "@regulator45",
    "@fakumadda1632",
    "@davidtomkins-y3w",
    "@TamaraStarnes-p2d",
    "@jaroslawprzybylski5517",
    "@marcusjohnson0417",
    "@leavitts77",
    "@sheasky",
    "@YouBetterBeYou",
    "@Serge-AndréRhéaumeSergio",
    "@nessuno6110",
    "@RogerIsaksson-nc3tj",
    "@mikeblubaugh8988",
    "@williehenson1935",
    "@simonkul98",
    "@potatochips5282",
    "@zacharyjackson3132",
    "@Designarchi1",
    "@KXT-z7g",
    "@therescueband3691"
  ],
  "0PBwWjaY_9M": [
    "@donsland1610",
    "@utilisateurm5182",
    "@bennodebruyn4344",
    "@kdog145",
    "@gyula5609",
    "@americanfreedom6417",
    "@JosephMeeks-d1b",
    "@ranjeetkolita9133",
    "@dennydecomble",
    "@A.e.m-qm9yi",
    "@elllad",
    "@gregebert3103",
    "@therescueband3691",
    "@davidwoo2244"
  ],
  "Q8Y77-kclT8": [
    "@jameslongstreet9259",
    "@VdL_508",
    "@franksanford1076",
    "@KobeCuter",
    "@edvidal3118",
    "@certaindeaf8315",
    "@brentpalkovic6079",
    "@theweeknder",
    "@desireejarrett2453",
    "@WyMustIGo"
  ],
  "h6cVAVWMDWM": [
    "@MrGreenlantern69man",
    "@420kushmaster"
  ],
  "v1TNuvXanxo": [
    "@drvoodoo3073",
    "@SharonDésirée-q8p",
    "@walbertjenkinson",
    "@rollerskatertexasgirl",
    "@JesusisKing-og1hv",
    "@carpetpunter158",
    "@pennypackmtb2542",
    "@ralphpangonis5473",
    "@dianedeatherage9401",
    "@sadwingsraging3044"
  ],
  "w-2f2tvCOIs": [
    "@rogergriffith-j2x",
    "@KDean22",
    "@charlesburkhart800",
    "@LorneChadwell",
    "@rodrigoveigacortes6046"
  ],
  "b2KD9MOsJ8I": [
    "@mcbingoitz8782",
    "@timkeenan9625",
    "@raydonica6723",
    "@bonyclifton181",
    "@VictorJeffcoat",
    "@sharonlee6229",
    "@Pancito49",
    "@handleyourface",
    "@LetsfixAmercia",
    "@Auntypatti",
    "@Neraxis-zero",
    "@stupidtube9",
    "@kathleenwalters6410",
    "@RobSparkman",
    "@petrafied.",
    "@IreneB-v5i",
    "@mchristr",
    "@MDK5000",
    "@frankenz66",
    "@Alaskabuilt_",
    "@nojindoj2334",
    "@msjanzzee",
    "@jameshildebrand907",
    "@lisettegarcia"
  ],
  "7yEsl4WpL5g": [
    "@stephenparsons8299",
    "@sabejreid2072",
    "@susanstevens976"
  ],
  "vJfXaA49P-Q": [
    "@goexplore4321",
    "@proximap2151",
    "@HiAuntchovie",
    "@bl8danjil",
    "@turnoffmainstream"
  ],
  "Df2LscavXUQ": [
    "@nashonnimitz9333",
    "@JenniferHobbs-e3s2u",
    "@radist8334",
    "@xXEnvyMawi",
    "@chriscarr422",
    "@DavidJioo",
    "@Autumnh141983",
    "@astropioneer3296",
    "@lanemiller1353",
    "@eliaspowell8864"
  ],
  "Cb99FBD1IY4": [
    "@lenrom10",
    "@Whitecranemaster1",
    "@victor77777771",
    "@1Biswet",
    "@kevin982",
    "@chriscarr422",
    "@nmr3852",
    "@guardianangel9517",
    "@lisettegarcia"
  ],
  "S1vAWBc_f9Y": [
    "@freemenownrifles8814",
    "@MortenAbildgaard-h2z",
    "@j2thek903",
    "@CoryMichael-v3f",
    "@glendagentry6153",
    "@fubokuen",
    "@Ravenyze",
    "@marioortiz7953",
    "@cwmode11",
    "@Lawleygagger",
    "@Pc31Gaming",
    "@ascaulesavunculo5589"
  ],
  "5qgbES8inoQ": [
    "@stingray427man",
    "@Thrunabulax10",
    "@MrSpeakerboxx05",
    "@famos59",
    "@GlennBlonshine",
    "@Wesleyp766",
    "@Carlos-m2v1w"
  ],
  "auThH7pQS6I": [
    "@hgee6311",
    "@williamelliott",
    "@kathleenlandry1953",
    "@mysticmeadowshomestead6209",
    "@BonnieSchneider-ue4bp",
    "@RC-eb5hq",
    "@sammyboy170",
    "@RedsDaddy",
    "@becca318",
    "@jackferguson3009",
    "@Babettenow",
    "@regulator45",
    "@RytSide",
    "@purrfection325"
  ],
  "5A21vRJNJ_c": [
    "@smoothtwh",
    "@Jon-hk6ln",
    "@cindyshafer1957",
    "@regulator45",
    "@2WingSamebird24",
    "@LetsfixAmercia"
  ],
  "qtR6iY-eO1A": [
    "@lornamartinez5961",
    "@NickiAnderson-i4i",
    "@anthonywinebarger1529",
    "@Peter-e5s",
    "@terencesommer6177",
    "@DionneRateau",
    "@douglasbrown7060",
    "@cheeseslice6264",
    "@Wreckerlife",
    "@hollymahler8213",
    "@JeffDepuy",
    "@ToDestroyTheWorksOfTheDevil",
    "@wtfflorida7976",
    "@edkurtz",
    "@walbertjenkinson",
    "@bambampk4052",
    "@NarvaNaomi62",
    "@cheribee968",
    "@ScottIngram-f4d",
    "@ValerieSimmons-y5z",
    "@shonisanirapea889",
    "@muaposala1041",
    "@WelshEnZo",
    "@Droneloverofirishskies",
    "@M.Boatwright",
    "@Jewls1000",
    "@dawnwells524",
    "@Ladywstria",
    "@CommonSenseGarage",
    "@willoverman-k8t",
    "@Randy-i7n1i",
    "@montepetersen2888",
    "@lindabaugus6839",
    "@yyyelo",
    "@mikeumpire698",
    "@aacalhoun4291",
    "@judymarquette8847",
    "@scriptkeeper89",
    "@blancahoward4477",
    "@devildog_actual",
    "@Valleygirl2112X",
    "@suky38",
    "@Sheepdog1314",
    "@MaryGoben",
    "@rafaiaa13",
    "@williammcateer1095",
    "@Iamcheesesandwich",
    "@susanb5637"
  ],
  "Zstk97D1QJE": [
    "@newellbarrett5537",
    "@mfwebpea2935",
    "@KevinPierce-pu4bd",
    "@rohanharridge5579",
    "@tanyawilliams1887",
    "@Sheepdog1314",
    "@ridgerunner955",
    "@chriscarr422",
    "@PippiBernstein",
    "@soylentgreen9492",
    "@wallacedaniel8918",
    "@MichelleArmstrong-lk5bc",
    "@errickmackey8983",
    "@reddmendoza6765",
    "@eltonwashington596",
    "@billie3054"
  ],
  "dhL01Oac8p0": [
    "@AllorNothing-",
    "@usausa3234",
    "@HiAuntchovie",
    "@LeDAR-321",
    "@thatsworrisome",
    "@turnoffmainstream",
    "@thenovicevoice",
    "@MarkFerrando-v4p",
    "@nspowers7130",
    "@certaindeaf8315",
    "@johan2day",
    "@adrianafit4098",
    "@tulipmcfay2939",
    "@rheamiller148",
    "@meetdogblack8277",
    "@Rocket39Smoke14",
    "@SunflowerWisdom",
    "@austindenotter19",
    "@johnr.lowther7718",
    "@raymequet7372",
    "@liven4happynus115",
    "@jcass1970",
    "@Absaalookemensch",
    "@larryphillips4164",
    "@bmiles2011",
    "@TrustTruth-Ok65"
  ],
  "z9zj8-g6AjM": [
    "@dudoodurs5",
    "@leelydston1225",
    "@madelonmartin5661",
    "@ScottG-e7n",
    "@yarevatan6706",
    "@LotsaTippingPoints",
    "@jessical7083",
    "@WillieDeanJohnsonJr-l1d",
    "@criticaltheories5222",
    "@imranquinn2070",
    "@dizners",
    "@DavidJioo",
    "@Hanna-h3n4k",
    "@787mysterio",
    "@DunklerKaiser",
    "@chriscarr422",
    "@caribbeanchild",
    "@wishusknight3009",
    "@beaucurtis7524",
    "@kevinmcleod3116",
    "@benbonesalive",
    "@brianhollings7963",
    "@flb-s1g",
    "@Shadygamer802",
    "@erwinpitigoi127",
    "@TheGurkan2",
    "@nhmooytis7058",
    "@Miniflicks89",
    "@highspot1306",
    "@michaelcharach"
  ],
  "2PLYUSVZvoM": [
    "@edkitchen8526",
    "@kwik2hear915",
    "@Whitecranemaster1",
    "@August84118",
    "@copisetic1104",
    "@ItsLifeLibertyFreedom",
    "@melissazimmerman7796",
    "@AcutePumpkinClodHopper",
    "@austindenotter19",
    "@shaesghostboo",
    "@Alaskabuilt_",
    "@johnmarkkillough6242",
    "@ranjeetkolita9133",
    "@cwmode11",
    "@regulator45",
    "@1940limited",
    "@annieoakley4795",
    "@DeborahGrantham-xh6dn"
  ],
  "RZJSJ4hD-b0": [
    "@aprilmillard-nd4xt",
    "@paulkurilecz4209",
    "@williamelliott",
    "@GGR741",
    "@TuLeeLee-st2",
    "@portgibson2747",
    "@JeneseMimiFisher",
    "@LAYNAtm",
    "@Ken-gz9ne",
    "@billhillyer334",
    "@stayhappy9893",
    "@nickmcintyre2679",
    "@citizenkane0014",
    "@markus332",
    "@denisehansen-iv2et",
    "@terrydodd-qb8tg"
  ],
  "7_ux8ncqs8I": [
    "@graydi66y",
    "@glassman164",
    "@AcutePumpkinClodHopper",
    "@paulgonzales9",
    "@colorman5657",
    "@sz7199"
  ],
  "ffaeG3e7dBE": [
    "@certaindeaf8315",
    "@Dwight.Courtney",
    "@beaucurtis7524",
    "@67swisslisa"
  ],
  "6adM8VXypvs": [
    "@phydeaux007",
    "@Rksports76",
    "@mirkograveho1388"
  ],
  "1vnwwqc-bnY": [
    "@robiamm9232",
    "@IraqwarwasaLie",
    "@doloresmendoza506",
    "@Theholetrollonpatrol",
    "@Telephonebill51"
  ],
  "1EDsZ1jnArc": [
    "@JpVicvega",
    "@harryayre9050",
    "@rheafernandez8131",
    "@DrDeepakKumarSingh-1_M",
    "@maggiecady8292",
    "@themanwithnoname7576",
    "@turnoffmainstream"
  ],
  "l_xUNoZmdGs": [
    "@JesusisKing-og1hv"
  ],
  "AU6kMsOpLPY": [
    "@dorkanubis",
    "@rollerskatertexasgirl",
    "@diabeteswithdev",
    "@Sheepdog1314",
    "@billhillyer334",
    "@regulator45"
  ],
  "MhYZON_zpF8": [
    "@becca318",
    "@itsoktolovechina"
  ],
  "e6D0Qg56Km4": [
    "@tortoisejohnny7227",
    "@glassontherocks",
    "@pivotpointfilms"
  ],
  "JDLYqkjRdV4": [
    "@torigoode5068",
    "@chriscarr422",
    "@monazacheis260",
    "@msjanzzee",
    "@dawnwells524",
    "@WKGWOMANINTN",
    "@sherriroberts2657"
  ],
  "eSINEIxrE_k": [
    "@walbertjenkinson",
    "@lisettegarcia",
    "@becca318",
    "@viking7084",
    "@markperry721"
  ],
  "x19jnJVu0tE": [
    "@jojohnson215",
    "@nortfroggirl",
    "@StevenBrogan-tt2sj",
    "@u.s.m.c.fewproudthemarines2987",
    "@rjohnson9543"
  ],
  "OK4OkZ_3LXQ": [
    "@whatwouldpicarddomakeitso9607",
    "@Sukisocks7",
    "@brokenwrench404",
    "@kathleenlandry1953",
    "@Zangetsu2026",
    "@Michelle-kj7wv",
    "@markbarkley3790",
    "@u.s.m.c.fewproudthemarines2987",
    "@nicoledavis7031",
    "@2AAWK"
  ],
  "0T6XDJOz3-w": [
    "@rissaroosdaddy1891",
    "@HiAuntchovie",
    "@slither42",
    "@kiwigal9654",
    "@jefferybuettgens4849",
    "@JTOTHEW3000",
    "@Matrixisreal69",
    "@kdel9776",
    "@michellouisgenor7742",
    "@brentdale5730",
    "@benjaminboyle7329",
    "@bryanbarnesNC",
    "@certaindeaf8315",
    "@paraintheworld",
    "@billhillyer334",
    "@joneslisa7886",
    "@jeremiahwasabullfrog1",
    "@bowwinkle6651",
    "@xoneeleven",
    "@jeffbrown1894",
    "@chriscarr422",
    "@diegobuns9133",
    "@muensfils9279",
    "@zGoodMan187z",
    "@stevelittlefield6956",
    "@wileye3142",
    "@rudee315",
    "@nomerompanlaspelotas5812",
    "@gerrykings187",
    "@stevenesmith4152",
    "@maasahrat",
    "@gangster3591",
    "@wheelsmcdealsace",
    "@CyborgBob",
    "@ShireIO",
    "@jhonfrancis.1"
  ]
}